[
  {
    "lemma": "chalk",
    "meanings_de": ["weiße Schreibkreide", "Kletterkreide"],
    "definitions_de": ["weiße, weiche Kalksteinsubstanz, die zu Stiften geformt wird und zum Schreiben auf Tafeln verwendet wird", "pulverisiertes Magnesiumkarbonat, das von Kletterern und Turnern zur Verbesserung des Griffs verwendet wird"],
    "examples_de": [["Der Lehrer schrieb die mathematische Gleichung mit **Kreide** an die Tafel", "Wir müssen noch bunte **Kreide** für das Klassenzimmer besorgen"], ["Sie trug **Magnesia** auf ihre Hände auf, bevor sie die schwierige Kletterroute versuchte", "Die **Kreidtasche** der Turnerin fiel während ihrer Übung herunter"]]
  },
  {
    "lemma": "chalkboard",
    "meanings_de": ["Schultafel"],
    "definitions_de": ["große, flache, dunkle Oberfläche, typischerweise aus Schiefer, die zum Schreiben mit Kreide verwendet wird"],
    "examples_de": [["Der Professor füllte die gesamte **Tafel** mit komplexen Gleichungen", "Jemand muss die **Schultafel** vor der nächsten Stunde säubern"], ["Die alte Schule verwendet noch traditionelle **Kreidetafeln** statt Whiteboards", "Sie zeichnete ein schönes Diagramm an die **Wandtafel**, um das Konzept zu erklären"]]
  },
  {
    "lemma": "challenger",
    "meanings_de": ["Herausforderer im Wettkampf", "Person die hinterfragt"],
    "definitions_de": ["Person, die gegen andere antritt, insbesondere um einen Titel oder eine Position", "jemand, der etablierte Ideen, Autoritäten oder Entscheidungen in Frage stellt oder bestreitet"],
    "examples_de": [["Der junge Boxer galt als ernsthafter **Herausforderer** für den Schwergewichtstitel", "Mehrere **Herausforderer** traten an, um sich für die Meisterschaft zu qualifizieren"], ["Sie wurde zur lautstarken **Kritikerin** der Umweltpolitik des Unternehmens", "Der Wissenschaftler war ein beharrlicher **Zweifler** an konventionellen Theorien"]]
  },
  {
    "lemma": "chameleon",
    "meanings_de": ["farbwechselnde Echse", "anpassungsfähige Person"],
    "definitions_de": ["kleine tropische Echse mit der Fähigkeit, ihre Hautfarbe an die Umgebung anzupassen", "Person, die ihr Verhalten oder ihre Meinungen ändert, um sich verschiedenen Situationen anzupassen"],
    "examples_de": [["Das **Chamäleon** wechselte langsam von Grün zu Braun auf dem Ast", "Wir entdeckten ein winziges **Chamäleon**, das sich zwischen den Blättern versteckte"], ["Er ist so ein politisches **Chamäleon**, das ständig seine Haltung ändert, um Wählern zu gefallen", "Sie war ein soziales **Chamäleon**, das sich in jede Gruppe einfügen konnte"]]
  },
  {
    "lemma": "champ",
    "meanings_de": ["umgangssprachlich Champion", "geräuschvoll beißen"],
    "definitions_de": ["informeller Begriff für Champion oder Sieger im Sport oder Wettbewerb", "Handlung des geräuschvollen und ungeduldigen Beißens oder Kauens"],
    "examples_de": [["Der Box-**Champion** verteidigte seinen Titel zum fünften Mal", "Alle wollten den neuen Schach-**Meister** kennenlernen"], ["Das Pferd **kaute** ungeduldig auf dem Gebiss herum und wollte endlich losrennen", "Er **kaute** nervös auf seiner Zigarre, während er auf die Ergebnisse wartete"]]
  },
  {
    "lemma": "champagne",
    "meanings_de": ["Schaumwein"],
    "definitions_de": ["perlender Weißwein aus der Champagne-Region Frankreichs oder ähnliche Weine aus anderen Regionen"],
    "examples_de": [["Sie öffneten eine Flasche **Champagner** zur Feier ihres Hochzeitstages", "Die Bläschen des **Champagners** kitzelten in ihrer Nase, als sie einen Schluck nahm"], ["Wir bestellten **Sekt** für den Mitternachtstoast zu Silvester", "Beim Hochzeitsempfang wurde teurer französischer **Champagner** serviert"]]
  },
  {
    "lemma": "chancellor",
    "meanings_de": ["Regierungschef", "Universitätsleiter"],
    "definitions_de": ["hochrangiger Regierungsbeamter, der in einigen Ländern oft als Regierungschef fungiert", "oberster Verwaltungsbeamter einer Universität oder Leiter bestimmter Bildungseinrichtungen"],
    "examples_de": [["Die deutsche **Bundeskanzlerin** verkündete auf dem Gipfel neue Wirtschaftspolitiken", "Sie diente zwölf Jahre als **Kanzlerin**, bevor sie in den Ruhestand ging"], ["Der **Universitätskanzler** leitete die Abschlussfeier", "Studenten protestierten vor dem Büro des **Rektors** gegen Studiengebührenerhöhungen"]]
  },
  {
    "lemma": "chancellorship",
    "meanings_de": ["Kanzleramt-Zeitraum"],
    "definitions_de": ["Amt, Position oder Amtszeit eines Kanzlers in Regierung oder Bildung"],
    "examples_de": [["Seine **Kanzlerschaft** war geprägt von bedeutenden Wirtschaftsreformen", "Sie erreichte viele Bildungsverbesserungen während ihrer **Amtszeit**"], ["Die Universität blühte unter ihrer zehnjährigen **Kanzlerschaft** auf", "Er schrieb Memoiren über seine Erfahrungen während der **Kanzlerschaft**"]]
  },
  {
    "lemma": "chandelier",
    "meanings_de": ["dekorative Deckenleuchte"],
    "definitions_de": ["verzierte hängende Leuchte mit mehreren Armen für Lichter oder Kerzen, die von der Decke hängt"],
    "examples_de": [["Der Kristall-**Kronleuchter** funkelte in der eleganten Atmosphäre des Ballsaals", "Sie reinigten vorsichtig jedes Teil des antiken **Lüsters**"], ["Ein massiver **Kronleuchter** hing von der bemalten Decke des Theaters", "Der **Lüster** schwankte sanft während des leichten Erdbebens"]]
  },
  {
    "lemma": "changeover",
    "meanings_de": ["Systemumstellung"],
    "definitions_de": ["Prozess des Wechsels von einem System, einer Methode oder Situation zu einer anderen"],
    "examples_de": [["Die **Umstellung** auf das neue Computersystem dauerte mehrere Wochen", "Wir hatten einige Probleme während der **Übergangsphase**"], ["Die Betriebsunterbrechung ermöglichte eine reibungslose **Umstellung** auf automatisierte Produktion", "Spieler wechseln beim **Seitenwechsel** im Tennis die Seiten"]]
  },
  {
    "lemma": "changer",
    "meanings_de": ["Wechselgerät", "Person die wechselt"],
    "definitions_de": ["mechanisches Gerät, das automatisch etwas wechselt, wie Schallplatten, CDs oder Geld", "Person, die Änderungen vornimmt oder eine Sache gegen eine andere austauscht"],
    "examples_de": [["Die alte Jukebox hatte einen mechanischen **Plattenwechsler** im Inneren", "Werfen Sie Münzen in den **Geldwechsler**, um Vierteldollar zu erhalten"], ["Sie arbeitete als **Geldwechslerin** in der Wechselstube", "Er war als **Wegbereiter** in der Technologiebranche bekannt"]]
  },
  {
    "lemma": "chant",
    "meanings_de": ["rhythmisch wiederholte Worte", "melodiöser religiöser Gesang"],
    "definitions_de": ["Wörter oder Phrasen, die rhythmisch wiederholt werden, oft von einer Menge oder Gruppe", "einfacher melodischer Gesang, besonders in religiösen Gottesdiensten mit begrenztem musikalischem Umfang"],
    "examples_de": [["Die Demonstranten hielten ihren **Sprechchor** stundenlang vor dem Gebäude aufrecht", "Die Menge brach nach dem Spiel in einen Sieges-**Gesang** aus"], ["Der morgendliche **Choral** der Mönche hallte durch die Klosterhallen", "Sie lernte den alten Sanskrit-**Gesang** von ihrer Yogalehrerin"]]
  },
  {
    "lemma": "chanter",
    "meanings_de": ["Person die singt", "Dudelsack-Melodiepfeife"],
    "definitions_de": ["Person, die Gesänge singt oder rezitiert, besonders in religiösen Kontexten", "Pfeife am Dudelsack, die mit Grifflöchern die Melodie spielt"],
    "examples_de": [["Der **Vorsänger** führte die Gemeinde durch die Abendgebete", "Buddhistische **Sänger** erfüllten den Tempel mit ihren rhythmischen Stimmen"], ["Er reinigte sorgfältig die **Spielpfeife** seines schottischen Dudelsacks", "Die **Melodiepfeife** erzeugt die Hauptmelodie, während die Bordune die Harmonie liefern"]]
  },
  {
    "lemma": "chanting",
    "meanings_de": ["rhythmische Stimmwiederholung"],
    "definitions_de": ["Akt des Singens oder Sprechens von Wörtern oder Lauten auf repetitive, rhythmische Weise, oft in Gruppen"],
    "examples_de": [["Das **Singen** der Menge wurde lauter, als das Team ein Tor erzielte", "Friedliches **Chanten** erfüllte die Luft während des Meditations-Retreats"], ["Das rhythmische **Singen** half den Arbeitern, ihr Tempo beizubehalten", "Religiöses **Chanten** wird seit Tausenden von Jahren praktiziert"]]
  },
  {
    "lemma": "chap",
    "meanings_de": ["umgangssprachlich männliche Person", "Hautriss"],
    "definitions_de": ["informeller britischer Begriff für einen Mann oder Jungen, oft freundlich verwendet", "Riss oder Rauheit in der Haut, verursacht durch kaltes Wetter oder übermäßige Trockenheit"],
    "examples_de": [["Er ist ein anständiger **Kerl**, der seinen Nachbarn immer hilft", "Der alte **Bursche** im Laden an der Ecke kennt jeden beim Namen"], ["Der kalte Winterwind verursachte schmerzhafte **Risse** auf ihren Lippen", "Verwenden Sie Feuchtigkeitscreme, um **aufgesprungene** Hände zu vermeiden"]]
  },
  {
    "lemma": "chapel",
    "meanings_de": ["kleines religiöses Gebäude"],
    "definitions_de": ["kleines Gebäude oder Raum für christliche Gottesdienste, oft Teil einer größeren Institution"],
    "examples_de": [["Die **Krankenhauskapelle** bot einen ruhigen Ort für Gebet und Besinnung", "Sie heirateten in der kleinen **Kapelle** auf dem Campus"], ["Die historische **Kapelle** stammt aus dem 14. Jahrhundert", "Schüler versammelten sich in der **Schulkapelle** zur Morgenandacht"]]
  },
  {
    "lemma": "chaperone",
    "meanings_de": ["erwachsene Aufsichtsperson"],
    "definitions_de": ["Erwachsener, der junge Menschen bei gesellschaftlichen Veranstaltungen begleitet und beaufsichtigt, um angemessenes Verhalten sicherzustellen"],
    "examples_de": [["Eltern-Freiwillige dienten als **Aufsichtspersonen** beim Schulball", "Die **Begleitperson** sorgte dafür, dass alle Schüler bis zur Sperrstunde in ihre Zimmer zurückkehrten"], ["Wir brauchen mehr **Aufsichtspersonen** für den bevorstehenden Ausflug", "Ihre Tante fungierte bei ihren ersten Verabredungen als **Anstandsdame**"]]
  },
  {
    "lemma": "chaplain",
    "meanings_de": ["Geistlicher in Institutionen"],
    "definitions_de": ["Mitglied des Klerus, das einer Militäreinheit, Institution oder privaten Kapelle zugeordnet ist und spirituelle Führung bietet"],
    "examples_de": [["Der **Krankenhausseelsorger** tröstete Familien im Wartezimmer", "Sie diente zehn Jahre als **Militärgeistliche**"], ["Der **Gefängnispfarrer** leitete wöchentliche Gottesdienste für Insassen", "Der **Schulkaplan** bot Beratung für problematische Schüler an"]]
  },
  {
    "lemma": "chaplaincy",
    "meanings_de": ["Kaplanamt-Position"],
    "definitions_de": ["Position, Amt oder Abteilung eines Kaplans innerhalb einer Institution oder Organisation"],
    "examples_de": [["Er nahm eine **Seelsorgestelle** an der örtlichen Universität an", "Die **Krankenhausseelsorge** betreut Patienten aller Glaubensrichtungen"], ["Sie schloss letztes Jahr ihre Ausbildung für die **Militärseelsorge** ab", "Das **Seelsorgeprogramm** bietet spirituelle Unterstützung für Studenten"]]
  },
  {
    "lemma": "char",
    "meanings_de": ["verbranntes geschwärztes Material", "Reinigungsperson", "Fischart"],
    "definitions_de": ["teilweise verbranntes oder geschwärztes Material, das durch unvollständige Verbrennung entsteht", "britischer Begriff für eine Person, die zum Reinigen von Häusern oder Büros angestellt ist", "Kaltwasserfisch ähnlich dem Lachs, der in nördlichen Seen vorkommt"],
    "examples_de": [["Das Feuer hinterließ **Kohlespuren** an der Küchendecke", "Sie fanden **verkohlte** Stücke im verlassenen Lagerfeuer"], ["Die **Putzfrau** des Büros kommt jeden Morgen früh zum Reinigen", "Sie arbeitete als **Reinigungskraft**, um ihre Familie zu unterstützen"], ["Frischer **Saibling** gilt in Alpenrestaurants als Delikatesse", "Sie fingen mehrere **Saiblinge** während ihres Angelausflugs"]]
  },
  {
    "lemma": "characterisation",
    "meanings_de": ["Charakterbeschreibung-Darstellung"],
    "definitions_de": ["britische Schreibweise von Charakterisierung, die beschreibt, wie Charaktere in Literatur oder Drama dargestellt werden"],
    "examples_de": [["Die **Charakterzeichnung** des Bösewichts durch den Autor war besonders überzeugend", "Kritiker lobten die subtile **Charakterdarstellung** des Films"], ["Ihre **Darstellung** der Lady Macbeth gewann mehrere Preise", "Dem Roman fehlt es an Tiefe in der **Charakterisierung** der Nebenfiguren"]]
  },
  {
    "lemma": "characterization",
    "meanings_de": ["Charakterbeschreibung-Darstellung"],
    "definitions_de": ["Prozess der Schaffung und Beschreibung von Charakteren in Literatur, Drama oder Film, einschließlich ihrer Eigenschaften und Motivationen"],
    "examples_de": [["Die **Charakterisierung** des Dramatikers erweckte jede Rolle zum Leben", "Starke **Figurenzeichnung** ist wesentlich für fesselndes Geschichtenerzählen"], ["Der Schauspieler studierte das Drehbuch sorgfältig, um die **Charakterisierung** seiner Rolle zu verstehen", "Kritiker bemerkten die oberflächliche **Figurendarstellung** der Nebenrollen"]]
  },
  {
    "lemma": "charade",
    "meanings_de": ["Vortäuschung oder Täuschung", "Ratespiel"],
    "definitions_de": ["aufwendige Vortäuschung oder täuschende Handlung, die dazu dient, die Wahrheit zu verbergen", "Partyspiel, bei dem Spieler Wörter oder Phrasen für andere zum Erraten vorspielen"],
    "examples_de": [["Ihre glückliche Ehe war nur eine **Scharade** für die Öffentlichkeit", "Er hielt die **Maskerade** aufrecht, reich zu sein, trotz seiner Schulden"], ["Wir spielten gestern Abend **Scharade** auf der Geburtstagsparty", "Sie war ausgezeichnet im **Pantomimenspiel** und erriet jede Phrase richtig"]]
  },
  {
    "lemma": "charcoal",
    "meanings_de": ["schwarzes Kohlenstoffmaterial", "dunkelgraue Farbe"],
    "definitions_de": ["schwarzer Kohlenstoffrückstand aus erhitztem Holz, verwendet als Brennstoff, zum Zeichnen oder Filtern", "dunkelgraue Farbe, die dem Farbton von Holzkohle ähnelt"],
    "examples_de": [["Künstler verwenden **Kohlestift** , um dramatische Schwarz-Weiß-Zeichnungen zu erstellen", "Wir brauchen mehr **Holzkohle** für das Wochenend-Barbecue"], ["Sie trug einen **anthrazitfarbenen** Anzug zum Geschäftstreffen", "Der **kohlegraue** Himmel drohte den ganzen Nachmittag mit Regen"]]
  },
  {
    "lemma": "chard",
    "meanings_de": ["Blattgemüse"],
    "definitions_de": ["grünes Blattgemüse mit farbigen Stielen, verwandt mit Rüben, auch Mangold genannt"],
    "examples_de": [["Sie briet bunten **Mangold** mit Knoblauch für eine gesunde Beilage", "Der Garten produzierte dieses Jahr schönen roten und gelben **Mangold**"], ["Frischer **Mangold** vom Bauernmarkt schmeckt besser als gekaufter", "Fügen Sie gehackten **Mangold** zu Suppen für zusätzliche Nährstoffe hinzu"]]
  },
  {
    "lemma": "charger",
    "meanings_de": ["elektronisches Ladegerät", "große Servierplatte", "Schlachtross"],
    "definitions_de": ["Gerät, das elektrische Energie liefert, um Batterien in Telefonen oder anderen Elektronikgeräten aufzuladen", "große flache Platte zum Servieren von Speisen oder als dekorative Unterlage unter Tellern", "historischer Begriff für starkes Pferd, das in Schlachten oder Turnieren verwendet wurde"],
    "examples_de": [["Vergiss nicht, dein **Handy-Ladegerät** für die Reise einzupacken", "Das **Laptop-Ladegerät** funktioniert nicht mehr und muss ersetzt werden"], ["Der Caterer arrangierte Vorspeisen auf silbernen **Platztellern**", "Jedes Gedeck beinhaltete einen dekorativen **Unterteller** unter dem Speiseteller"], ["Das **Streitross** des Ritters war für den Kampf ausgebildet", "Mittelalterliche Gemälde zeigten oft Krieger auf ihren **Schlachtrössern**"]]
  },
  {
    "lemma": "chariot",
    "meanings_de": ["antikes Radfahrzeug"],
    "definitions_de": ["zweirädriges, von Pferden gezogenes Fahrzeug, das in der antiken Kriegsführung und bei Rennen verwendet wurde"],
    "examples_de": [["Die römischen **Wagenrennen** zogen riesige Menschenmengen ins Kolosseum", "Archäologen entdeckten Überreste eines altägyptischen **Streitwagens**"], ["Die Museumsausstellung zeigt einen rekonstruierten griechischen **Kampfwagen**", "Ben-Hur enthielt eine berühmte **Wagenrennen**-Szene"]]
  },
  {
    "lemma": "charioteer",
    "meanings_de": ["Wagenlenker"],
    "definitions_de": ["Person, die einen Streitwagen fährt, besonders bei antiken Rennen oder in der Kriegsführung"],
    "examples_de": [["Der geschickte **Wagenlenker** gewann viele Rennen im alten Rom", "Ägyptische Grabmalereien zeigten oft den Pharao als **Wagenfahrer**"], ["Der **Wagenlenker** kämpfte darum, seine Pferde in der Kurve zu kontrollieren", "Berühmte **Wagenlenker** waren Berühmtheiten in der antiken Welt"]]
  },
  {
    "lemma": "charisma",
    "meanings_de": ["fesselnder persönlicher Magnetismus"],
    "definitions_de": ["besonderer magnetischer Charme oder Anziehungskraft, die Hingabe inspiriert und andere natürlich anzieht"],
    "examples_de": [["Das natürliche **Charisma** der Politikerin half ihr, die Wahl zu gewinnen", "Sein **Charisma** machte ihn zu einem erfolgreichen Motivationsredner"], ["Sie hatte die Art von **Ausstrahlung**, die jeden Raum erleuchtete", "Führung erfordert mehr als nur **Charisma**, um effektiv zu sein"]]
  },
  {
    "lemma": "charlatan",
    "meanings_de": ["betrügerischer Hochstapler"],
    "definitions_de": ["Person, die fälschlicherweise behauptet, besonderes Wissen oder Fähigkeiten zu haben, um andere zu täuschen"],
    "examples_de": [["Der angebliche Hellseher wurde als **Scharlatan** entlarvt, der Trauer ausnutzte", "Viele **Scharlatane** behaupten, Wunderheilungen für schwere Krankheiten zu haben"], ["Die Kunstwelt ist voller **Betrüger**, die gefälschte Meisterwerke verkaufen", "Er wurde als **Hochstapler** ohne medizinische Ausbildung enthüllt"]]
  },
  {
    "lemma": "charlotte",
    "meanings_de": ["geformtes Dessert", "weiblicher Name"],
    "definitions_de": ["kaltes Dessert aus Früchten und Brot oder Löffelbiskuits, in einer Form geformt", "häufiger weiblicher Vorname französischen Ursprungs"],
    "examples_de": [["Der Koch bereitete eine köstliche **Apfelcharlotte** zum Nachtisch zu", "**Erdbeercharlotte** ist eine klassische Sommerleckerei"], ["**Charlotte** wurde nach ihrer Großmutter benannt", "Prinzessin **Charlotte** steht an vierter Stelle in der britischen Thronfolge"]]
  },
  {
    "lemma": "charmer",
    "meanings_de": ["Person die bezaubert"],
    "definitions_de": ["Person, die Charme einsetzt, um andere zu beeinflussen oder anzuziehen, oft mit romantischer Absicht"],
    "examples_de": [["Er war ein richtiger **Charmeur** bei gesellschaftlichen Veranstaltungen", "Der **Schlangenbeschwörer** trat für Touristen auf dem Markt auf"], ["Sie erkannte ihn als **Schmeichler**, dem man nicht trauen konnte", "Dieser kleine Junge ist ein echter **Herzensbrecher** mit seinem Lächeln"]]
  },
  {
    "lemma": "chartreuse",
    "meanings_de": ["gelbgrüne Farbe", "Kräuterlikör"],
    "definitions_de": ["leuchtend gelbgrüne Farbe, benannt nach dem Likör", "französischer Kräuterlikör, hergestellt von Kartäusermönchen in grünen oder gelben Varianten"],
    "examples_de": [["Sie strich die Akzentwand in einem kräftigen **Chartreuse**-Ton", "Das **gelbgrüne** Kleid fiel bei der Modenschau auf"], ["Sie servierten **Chartreuse** als Digestif nach dem Abendessen", "Das Kloster produziert noch immer authentischen **Chartreuse**-Likör"]]
  },
  {
    "lemma": "chaser",
    "meanings_de": ["Getränk nach Alkohol", "Person die verfolgt"],
    "definitions_de": ["mildes Getränk, das unmittelbar nach starkem Alkohol konsumiert wird, um den Gaumen zu reinigen", "Person oder Sache, die jemanden oder etwas jagt oder verfolgt"],
    "examples_de": [["Er bestellte ein Bier als **Nachspüler** nach seinem Whiskey-Shot", "Limettensaft ist ein guter **Nachtrunk** für Tequila"], ["Der **Sturmjäger** folgte Tornados, um sie zu studieren", "Die **Verfolger** der Polizei rasten hinter dem flüchtenden Verdächtigen her"]]
  },
  {
    "lemma": "chasm",
    "meanings_de": ["tiefe Spalte Öffnung", "weiter Unterschied"],
    "definitions_de": ["tiefer Riss oder Öffnung in der Erdoberfläche wie eine Schlucht oder ein Abgrund", "tiefgreifender Unterschied oder Kluft zwischen Menschen, Meinungen oder Situationen"],
    "examples_de": [["Das Erdbeben schuf eine gefährliche **Schlucht** in der Bergstraße", "Sie überquerten vorsichtig die schmale Brücke über den **Abgrund**"], ["Es gibt eine wachsende **Kluft** zwischen Arm und Reich in der Gesellschaft", "Die **Kluft** zwischen ihren politischen Ansichten schien unüberbrückbar"]]
  },
  {
    "lemma": "chassis",
    "meanings_de": ["Fahrzeugrahmenstruktur"],
    "definitions_de": ["Grundrahmen eines Kraftfahrzeugs, der die Karosserie und mechanische Teile trägt"],
    "examples_de": [["Der Mechaniker untersuchte das **Fahrgestell** des Autos auf Rostschäden", "Dieser Lastwagen hat ein verstärktes **Chassis** für schwere Lasten"], ["Das leichte **Fahrgestell** des Rennwagens verbesserte seine Geschwindigkeit", "Ingenieure entwarfen ein neues **Chassis** für das Elektrofahrzeug"]]
  },
  {
    "lemma": "chastity",
    "meanings_de": ["sexuelle Enthaltsamkeit Tugend"],
    "definitions_de": ["Zustand der Enthaltung von sexueller Aktivität oder Qualität der Reinheit in Gedanken und Verhalten"],
    "examples_de": [["Mittelalterliche Ritter legten **Keuschheitsgelübde** zusammen mit anderen Eiden ab", "Einige religiöse Orden verlangen lebenslange **Keuschheit** von Mitgliedern"], ["Das Konzept der **Keuschheit** variiert zwischen verschiedenen Kulturen", "Die viktorianische Gesellschaft legte großen Wert auf weibliche **Keuschheit**"]]
  },
  {
    "lemma": "chateau",
    "meanings_de": ["französisches Schloss Anwesen"],
    "definitions_de": ["großes französisches Landhaus oder Schloss, oft mit Weingütern verbunden"],
    "examples_de": [["Sie besichtigten mehrere **Schlösser** im Loiretal", "Der Hochzeitsempfang fand in einem wunderschönen **Château** statt"], ["Dieser Wein stammt aus einem berühmten Bordeaux-**Château**", "Das **Schloss** ist seit Jahrhunderten im Familienbesitz"]]
  },
  {
    "lemma": "chatter",
    "meanings_de": ["schnelles informelles Gerede", "Zähneklappern"],
    "definitions_de": ["kontinuierliches schnelles informelles Reden über unwichtige Dinge", "schnelles Klickgeräusch von Zähnen bei Kälte oder vibrierenden mechanischen Teilen"],
    "examples_de": [["Das ständige **Geplapper** in der Cafeteria machte es schwer, sich zu konzentrieren", "Ihr nervöses **Geschwätz** füllte jede Stille im Gespräch"], ["Seine Zähne begannen in der eisigen Kälte zu **klappern**", "Das **Rattern** der Maschine deutete darauf hin, dass etwas locker war"]]
  },
  {
    "lemma": "chattering",
    "meanings_de": ["kontinuierliches schnelles Reden"],
    "definitions_de": ["Akt des schnellen und kontinuierlichen Redens, oft über triviale Dinge oder das Erzeugen schneller Geräusche"],
    "examples_de": [["Das **Geschwätz** aufgeregter Schüler erfüllte den Flur", "Eichhörnchen **schnattern** laut in der Eiche"], ["Ihr ständiges **Geplapper** während des Films störte andere Zuschauer", "Das **Zähneklappern** verriet, wie kalt ihm war"]]
  },
  {
    "lemma": "chauffeur",
    "meanings_de": ["professioneller Fahrer"],
    "definitions_de": ["Person, die angestellt ist, um ein privates Auto für jemand anderen zu fahren, besonders Luxusfahrzeuge"],
    "examples_de": [["Der **Chauffeur** öffnete die Limousinen-Tür für die Berühmtheit", "Sie engagierte einen **Fahrer** für ihren Hochzeitstag-Transport"], ["Das Hotel bietet einen **Chauffeur-Service** zum Flughafen", "Er arbeitete als **Privatfahrer** für wohlhabende Familien"]]
  },
  {
    "lemma": "chauvinism",
    "meanings_de": ["übertriebener patriotischer Stolz", "männlicher Überlegenheitsglaube"],
    "definitions_de": ["übermäßige oder voreingenommene Loyalität gegenüber dem eigenen Land, der Gruppe oder Sache", "Überzeugung, dass Männer Frauen überlegen sind, oft als männlicher Chauvinismus bezeichnet"],
    "examples_de": [["Sein Nationalismus überschritt die Grenze zu gefährlichem **Chauvinismus**", "Kultureller **Chauvinismus** hindert Menschen daran, andere Gesellschaften zu schätzen"], ["Die **chauvinistische** Kultur des Unternehmens führte zu Diskriminierungsklagen", "Männlicher **Chauvinismus** wurde in vergangenen Jahrzehnten offener zum Ausdruck gebracht"]]
  },
  {
    "lemma": "cheater",
    "meanings_de": ["Person die betrügt"],
    "definitions_de": ["Person, die unehrlich handelt, um einen Vorteil zu erlangen, besonders bei Spielen, Tests oder Beziehungen"],
    "examples_de": [["Der Lehrer erwischte den **Betrüger** beim Abschreiben während der Prüfung", "Online-Spiele haben Systeme, um **Schummler** zu erkennen und zu sperren"], ["Sie entdeckte durch Textnachrichten, dass ihr Freund ein **Betrüger** war", "Niemand will mit einem bekannten **Schummler** Karten spielen"]]
  },
  {
    "lemma": "cheating",
    "meanings_de": ["unehrliches Vorteilssuchen"],
    "definitions_de": ["Akt des unehrlichen Verhaltens, um unfairen Vorteil bei Prüfungen, Spielen oder Beziehungen zu erlangen"],
    "examples_de": [["**Schummeln** bei Prüfungen kann zu akademischer Suspendierung führen", "Der Skandal enthüllte weit verbreitetes **Betrügen** im Profisport"], ["Sie beendete die Beziehung nach der Entdeckung seines **Fremdgehens**", "**Mogeln** beim Kartenspiel führt zum Ausschluss aus dem Casino"]]
  },
  {
    "lemma": "checker",
    "meanings_de": ["Person die prüft", "Spielstein", "Musterviereck"],
    "definitions_de": ["Person, die etwas untersucht oder überprüft, besonders an der Ladenkasse", "flacher runder Stein, der im Damespiel verwendet wird", "ein Quadrat in einem Schachbrettmuster mit abwechselnden Farben"],
    "examples_de": [["Der **Qualitätsprüfer** inspizierte jedes Produkt vor dem Versand", "Die **Kassiererin** scannte die Artikel schnell"], ["Sie bewegte ihren **Spielstein** diagonal über das Brett", "Er machte seinen **Damestein** zur Dame, als er das andere Ende erreichte"], ["Der Boden hatte ein schwarz-weißes **Schachbrettmuster**", "Jedes **Feld** auf dem Brett war sorgfältig bemalt"]]
  },
  {
    "lemma": "checkerboard",
    "meanings_de": ["Spielbrett-Muster"],
    "definitions_de": ["quadratisches Brett mit abwechselnd farbigen Feldern, verwendet für Dame oder Schach"],
    "examples_de": [["Sie stellten das **Damebrett** für ihr Abendspiel auf", "Der Küchenboden ähnelte einem riesigen **Schachbrett**"], ["Sie malte ein **Schachbrettmuster** auf den Tisch", "Die Felder sahen aus dem Flugzeug wie ein **Schachbrett** aus"]]
  },
  {
    "lemma": "checklist",
    "meanings_de": ["Prüf-Aufgabenliste"],
    "definitions_de": ["schriftliche Liste von Elementen, die in systematischer Reihenfolge überprüft, abgeschlossen oder erinnert werden sollen"],
    "examples_de": [["Der Pilot ging die Vorflug-**Checkliste** sorgfältig durch", "Sie erstellte eine **Checkliste** mit Dingen, die sie für den Urlaub einpacken musste"], ["Die Operations-**Checkliste** hilft, medizinische Fehler zu vermeiden", "Vervollständigen Sie jeden Punkt auf der **Prüfliste**, bevor Sie einreichen"]]
  },
  {
    "lemma": "checkmate",
    "meanings_de": ["Schach-Gewinnstellung"],
    "definitions_de": ["Position im Schach, bei der der gegnerische König unmittelbar geschlagen werden kann und kein Entkommen möglich ist"],
    "examples_de": [["Sie verkündete **Schachmatt** in nur fünfzehn Zügen", "Der Großmeister sah das **Matt** drei Züge im Voraus kommen"], ["Er studierte berühmte **Schachmatt**-Muster, um sein Spiel zu verbessern", "Das unerwartete **Matt** überraschte sogar erfahrene Spieler"]]
  }
]