[
  {
    "lemma": "stationery",
    "meanings_de": ["Schreibwaren"],
    "definitions_de": ["Materialien zum Schreiben wie Papier, Briefumschläge und Stifte, die für Korrespondenz und Büroarbeiten verwendet werden"],
    "examples_de": [["Im Schreibwarengeschäft findet man hochwertiges **Briefpapier** für jeden Anlass", "Sie kaufte edles **Schreibpapier** für die Hochzeitseinladungen"]]
  },
  {
    "lemma": "stationmaster",
    "meanings_de": ["Bahnhofsvorsteher"],
    "definitions_de": ["Person, die für den Betrieb und die Organisation eines Bahnhofs verantwortlich ist"],
    "examples_de": [["Der **Bahnhofsvorsteher** kündigte die Verspätung des Schnellzugs an", "Wir sprachen mit dem **Bahnhofsvorsteher** über das Fundbüro"]]
  },
  {
    "lemma": "statistic",
    "meanings_de": ["Statistikwert"],
    "definitions_de": ["Einzelne numerische Information, die für Analysen oder als Referenz gesammelt wird"],
    "examples_de": [["Diese **Statistik** über die Arbeitslosigkeit überraschte alle im Meeting", "Jeder **Statistikwert** im Bericht muss ordnungsgemäß überprüft werden"]]
  },
  {
    "lemma": "statistician",
    "meanings_de": ["Statistiker"],
    "definitions_de": ["Fachperson, die numerische Daten mit mathematischen Methoden sammelt, analysiert und interpretiert"],
    "examples_de": [["Das Unternehmen stellte einen **Statistiker** zur Analyse der Markttrends ein", "Der **Statistiker** unseres Teams sagte die Wahlergebnisse präzise voraus"]]
  },
  {
    "lemma": "statuary",
    "meanings_de": ["Statuensammlung"],
    "definitions_de": ["Gesamtheit von Statuen oder die Kunst der Herstellung von Statuen aus Stein oder Metall"],
    "examples_de": [["Die antike griechische **Statuensammlung** des Museums zieht Tausende Besucher an", "Die **Bildhauerkunst** der Renaissance stellte oft religiöse und mythologische Themen dar"]]
  },
  {
    "lemma": "statuette",
    "meanings_de": ["kleine Dekorationsstatue"],
    "definitions_de": ["Kleine Statue, die als Dekoration oder Auszeichnung verwendet wird"],
    "examples_de": [["Sie stellte die Porzellan-**Statuette** vorsichtig auf den Kaminsims", "Das Filmfestival verleiht goldene **Statuetten** an die Gewinnerregisseure"]]
  },
  {
    "lemma": "stature",
    "meanings_de": ["Körpergröße", "Ansehen"],
    "definitions_de": ["Natürliche Größe einer Person im aufrechten Stand", "Grad des Respekts oder der Bedeutung in Gesellschaft oder Beruf"],
    "examples_de": [["Die beeindruckende **Statur** des Basketballspielers ließ ihn herausstechen", "Ihre kleine **Körpergröße** hinderte sie nicht am sportlichen Erfolg"], ["Der Wissenschaftler erlangte nach dem Nobelpreis internationale **Geltung**", "Sein **Ansehen** in der Gemeinde wuchs durch seine Wohltätigkeitsarbeit"]]
  },
  {
    "lemma": "stave",
    "meanings_de": ["Fassdaube", "Notensystem"],
    "definitions_de": ["Gebogene Holzleiste, die Teil eines Fasses oder Behälters bildet", "Satz von fünf horizontalen Linien, auf denen Musiknoten geschrieben werden"],
    "examples_de": [["Der Küfer ersetzte eine gebrochene **Daube** im Weinfass", "Jede **Fassdaube** muss perfekt passen, um Lecks zu verhindern"], ["Die Schüler lernten, Noten auf dem **Notensystem** zu lesen", "Der Komponist schrieb komplexe Melodien über mehrere **Notenlinien**"]]
  },
  {
    "lemma": "stead",
    "meanings_de": ["Stelle oder Position"],
    "definitions_de": ["Position oder Rolle, die jemand oder etwas einnehmen oder ausfüllen sollte"],
    "examples_de": [["Sein Assistent nahm an seiner **Stelle** am Meeting teil", "Die neue Technologie wird uns gute **Dienste** leisten"]]
  },
  {
    "lemma": "steakhouse",
    "meanings_de": ["Steakrestaurant"],
    "definitions_de": ["Restaurant, das sich auf das Servieren von Steaks und anderen Rindfleischgerichten spezialisiert hat"],
    "examples_de": [["Sie feierten ihren Jahrestag in einem gehobenen **Steakhaus** in der Innenstadt", "Das **Steakrestaurant** ist für seine Auswahl an trocken gereiftem Rindfleisch bekannt"]]
  },
  {
    "lemma": "stealer",
    "meanings_de": ["Dieb"],
    "definitions_de": ["Person, die das Eigentum einer anderen Person ohne Erlaubnis nimmt"],
    "examples_de": [["Die Überwachungskameras halfen, den Fahrrad**dieb** schnell zu identifizieren", "Der Aufmerksamkeits**dieb** unterbricht während Präsentationen ständig andere"]]
  },
  {
    "lemma": "stealing",
    "meanings_de": ["Diebstahl"],
    "definitions_de": ["Handlung des Nehmens fremden Eigentums ohne Erlaubnis oder rechtliche Grundlage"],
    "examples_de": [["Der Ladenbesitzer meldete mehrere Fälle von **Diebstahl**", "**Diebstahl** aus der Firma führte zur sofortigen Kündigung"]]
  },
  {
    "lemma": "stealth",
    "meanings_de": ["heimliche Bewegung"],
    "definitions_de": ["Vorsichtige und geheime Handlung oder Bewegung, um Entdeckung zu vermeiden"],
    "examples_de": [["Die Katze bewegte sich mit **Heimlichkeit** auf den ahnungslosen Vogel zu", "Militäroperationen erfordern oft **Tarnung** zum Erfolg"]]
  },
  {
    "lemma": "steamboat",
    "meanings_de": ["Dampfboot"],
    "definitions_de": ["Boot, das von einer Dampfmaschine angetrieben wird, besonders auf Flüssen verwendet"],
    "examples_de": [["Mark Twain schrieb über das Leben auf Mississippi-**Dampfbooten**", "Das alte **Dampfschiff** bietet jeden Sommer noch malerische Rundfahrten an"]]
  },
  {
    "lemma": "steamer",
    "meanings_de": ["Dampfschiff", "Dampfgarer"],
    "definitions_de": ["Großes Schiff, das von Dampfmaschinen für Ozeanreisen angetrieben wird", "Küchengerät, das Speisen mit Dampf aus kochendem Wasser gart"],
    "examples_de": [["Einwanderer kamen mit überfüllten **Dampfern** in Amerika an", "Der Luxus**dampfer** überquerte den Atlantik in fünf Tagen"], ["Sie bereitete gesundes Gemüse in ihrem Bambus-**Dampfgarer** zu", "Das Dim-Sum-Restaurant serviert Teigtaschen in traditionellen **Dampfkörbchen**"]]
  },
  {
    "lemma": "steampunk",
    "meanings_de": ["retrofuturistisches Genre"],
    "definitions_de": ["Science-Fiction-Genre mit dampfbetriebener Technologie in viktorianischen Umgebungen"],
    "examples_de": [["Ihr **Steampunk**-Kostüm beinhaltete eine Schutzbrille und Messingzahnräder", "Der **Steampunk**-Roman stellte sich dampfbetriebene Luftschiffe vor"]]
  },
  {
    "lemma": "steamship",
    "meanings_de": ["Dampfschiff"],
    "definitions_de": ["Großes Schiff, das von Dampfmaschinen für Passagier- oder Frachttransport angetrieben wird"],
    "examples_de": [["Das historische **Dampfschiff** wurde in ein Museum umgewandelt", "Die transatlantische **Dampfschifffahrt** revolutionierte den internationalen Handel"]]
  },
  {
    "lemma": "steed",
    "meanings_de": ["Reitpferd"],
    "definitions_de": ["Pferd, besonders ein temperamentvolles, das zum Reiten verwendet wird"],
    "examples_de": [["Der Ritter bestieg sein treues **Ross** vor der Schlacht", "Ihr weißes **Streitross** galoppierte anmutig über das Feld"]]
  },
  {
    "lemma": "steelman",
    "meanings_de": ["Stahlarbeiter"],
    "definitions_de": ["Person, die in der Stahlproduktion oder -verarbeitung arbeitet"],
    "examples_de": [["Sein Großvater arbeitete vierzig Jahre als **Stahlarbeiter**", "Der **Stahlwerker** trug Schutzausrüstung gegen die intensive Hitze"]]
  },
  {
    "lemma": "steeper",
    "meanings_de": ["Ziehgefäß"],
    "definitions_de": ["Behälter oder Gerät zum Ziehen oder Einweichen von etwas in Flüssigkeit"],
    "examples_de": [["Lassen Sie die Teeblätter fünf Minuten im **Teesieb** ziehen", "Der Kaffee-**Zubereiter** produziert einen weichen, reichhaltigen Geschmack"]]
  },
  {
    "lemma": "steeple",
    "meanings_de": ["Kirchturm"],
    "definitions_de": ["Hohe spitze Struktur auf einem Kirchengebäude, oft mit Glocken"],
    "examples_de": [["Der **Kirchturm** war kilometerweit sichtbar", "Der Blitz schlug gestern während des Gewitters in den **Kirchturmspitze** ein"]]
  },
  {
    "lemma": "steeplechase",
    "meanings_de": ["Hindernispferderennen"],
    "definitions_de": ["Pferderennen über eine Strecke mit Hindernissen einschließlich Zäunen und Wassergräben"],
    "examples_de": [["Das **Hindernisrennen** erfordert sowohl Geschwindigkeit als auch Sprungvermögen", "Sie trainierte ihr Pferd speziell für **Jagdrennen**-Wettbewerbe"]]
  },
  {
    "lemma": "steer",
    "meanings_de": ["junger Ochse"],
    "definitions_de": ["Kastriertes männliches Rind, das für die Fleischproduktion aufgezogen wird"],
    "examples_de": [["Der Rancher trennte die **Ochsen** von den Zuchtbullen", "Diese **Mastochsen** werden im nächsten Frühjahr marktreif sein"]]
  },
  {
    "lemma": "steerage",
    "meanings_de": ["Zwischendeck"],
    "definitions_de": ["Billigste Passagierunterbringung auf einem Schiff, historisch im Heck"],
    "examples_de": [["Viele Einwanderer reisten in überfüllten **Zwischendeck**-Abteilungen nach Amerika", "Die Passagiere im **Zwischendeck** ertrugen harte Bedingungen während der Ozeanüberquerungen"]]
  },
  {
    "lemma": "steering",
    "meanings_de": ["Lenksystem"],
    "definitions_de": ["Mechanismus oder Handlung zur Kontrolle der Richtung eines Fahrzeugs oder Schiffs"],
    "examples_de": [["Die **Servolenkung** des Autos erleichtert das Einparken erheblich", "Die richtige **Lenktechnik** ist für sicheres Fahren unerlässlich"]]
  },
  {
    "lemma": "stein",
    "meanings_de": ["Bierkrug"],
    "definitions_de": ["Großer Krug für Bier, traditionell aus Keramik mit Klappdeckel"],
    "examples_de": [["Er sammelte dekorative **Bierkrüge** von verschiedenen Brauereien", "Der Oktoberfest-**Maßkrug** fasste einen ganzen Liter Bier"]]
  },
  {
    "lemma": "stench",
    "meanings_de": ["Gestank"],
    "definitions_de": ["Starker und sehr unangenehmer Geruch, der Unbehagen verursacht"],
    "examples_de": [["Der **Gestank** vom Müllwagen erfüllte die Straße", "Wir konnten den **Gestank** aus dem Keller nicht ignorieren"]]
  },
  {
    "lemma": "stencil",
    "meanings_de": ["Schablone"],
    "definitions_de": ["Dünnes Blatt mit ausgeschnittenem Design zum Auftragen von Mustern mit Farbe oder Tinte"],
    "examples_de": [["Sie benutzte eine **Schablone**, um Blumen an die Wand zu malen", "Der Künstler schuf komplizierte Designs mit handgefertigten **Schablonen**"]]
  },
  {
    "lemma": "stenographer",
    "meanings_de": ["Stenograf"],
    "definitions_de": ["Person, die in der Kurzschrift bewandert ist und diese transkribiert"],
    "examples_de": [["Der Gerichts**stenograf** zeichnete jedes Wort der Aussage auf", "Vor der Computerzeit brauchte jeder Geschäftsführer einen geschickten **Stenografen**"]]
  },
  {
    "lemma": "stent",
    "meanings_de": ["medizinisches Röhrchen"],
    "definitions_de": ["Kleines Netzröhrchen, das in Blutgefäße oder Kanäle eingesetzt wird, um sie offen zu halten"],
    "examples_de": [["Der Arzt setzte einen **Stent** ein, um die blockierte Arterie zu öffnen", "Sein Herz-**Stent** hat den Blutfluss erheblich verbessert"]]
  },
  {
    "lemma": "stepbrother",
    "meanings_de": ["Stiefbruder"],
    "definitions_de": ["Sohn des Stiefelternteils aus einer früheren Beziehung"],
    "examples_de": [["Sein **Stiefbruder** kam zur Familie, nachdem seine Mutter wieder geheiratet hatte", "Die **Stiefbrüder** wurden trotz des Altersunterschieds enge Freunde"]]
  },
  {
    "lemma": "stepdaughter",
    "meanings_de": ["Stieftochter"],
    "definitions_de": ["Tochter des Ehepartners aus einer früheren Beziehung"],
    "examples_de": [["Sie behandelt ihre **Stieftochter** mit derselben Liebe wie ihre leiblichen Kinder", "Seine **Stieftochter** bat ihn, sie zum Altar zu führen"]]
  },
  {
    "lemma": "stepfather",
    "meanings_de": ["Stiefvater"],
    "definitions_de": ["Mann, der mit der Mutter verheiratet ist, aber nicht der biologische Vater ist"],
    "examples_de": [["Ihr **Stiefvater** brachte ihr das Fahrradfahren bei", "Der **Stiefvater** adoptierte die Kinder seiner Frau nach ihrer Hochzeit"]]
  },
  {
    "lemma": "stepmother",
    "meanings_de": ["Stiefmutter"],
    "definitions_de": ["Frau, die mit dem Vater verheiratet ist, aber nicht die biologische Mutter ist"],
    "examples_de": [["Die **Stiefmutter** arbeitete hart daran, Vertrauen zu ihrer neuen Familie aufzubauen", "Märchen stellen **Stiefmütter** oft unfairerweise als Bösewichte dar"]]
  },
  {
    "lemma": "steppe",
    "meanings_de": ["Graslandebene"],
    "definitions_de": ["Großes Gebiet flachen, unbewaldeten Graslandes in Südosteuropa oder Sibirien"],
    "examples_de": [["Nomadenstämme durchstreifen seit Jahrhunderten die mongolische **Steppe**", "Die weite **Steppe** erstreckte sich endlos unter dem klaren Himmel"]]
  },
  {
    "lemma": "stepper",
    "meanings_de": ["Trainingsgerät"],
    "definitions_de": ["Fitnessgerät, das das Treppensteigen für Herz-Kreislauf-Training simuliert"],
    "examples_de": [["Sie benutzt den **Stepper** im Fitnessstudio täglich dreißig Minuten", "Der Mini-**Stepper** passt perfekt in ihre kleine Wohnung"]]
  },
  {
    "lemma": "stepsister",
    "meanings_de": ["Stiefschwester"],
    "definitions_de": ["Tochter des Stiefelternteils aus einer früheren Beziehung"],
    "examples_de": [["Ihre **Stiefschwester** wurde über die Jahre zu ihrer besten Freundin", "Die **Stiefschwestern** teilten sich ein Zimmer, nachdem ihre Eltern geheiratet hatten"]]
  },
  {
    "lemma": "stepson",
    "meanings_de": ["Stiefsohn"],
    "definitions_de": ["Sohn des Ehepartners aus einer früheren Beziehung"],
    "examples_de": [["Er trainierte jedes Wochenende die Fußballmannschaft seines **Stiefsohns**", "Der **Stiefsohn** akzeptierte allmählich den neuen Mann seiner Mutter"]]
  },
  {
    "lemma": "stereo",
    "meanings_de": ["Soundsystem"],
    "definitions_de": ["Elektronisches Gerät zum Abspielen aufgenommener Musik mit Klang aus zwei Lautsprechern"],
    "examples_de": [["Sie kauften eine neue **Stereoanlage** für ihr Wohnzimmer", "Die Auto-**Stereoanlage** spielte während der Fahrt ihre Lieblingslieder"]]
  },
  {
    "lemma": "stereotype",
    "meanings_de": ["vereinfachtes Vorurteil"],
    "definitions_de": ["Weit verbreitetes, aber festes und vereinfachtes Bild oder Vorstellung von einer bestimmten Art von Person oder Sache"],
    "examples_de": [["Wir müssen schädliche **Vorurteile** über verschiedene Kulturen hinterfragen", "Der Film verstärkte leider veraltete Geschlechter**klischees**"]]
  },
  {
    "lemma": "sterilisation",
    "meanings_de": ["Dekontaminierungsprozess"],
    "definitions_de": ["Prozess, bei dem etwas von Bakterien oder anderen lebenden Mikroorganismen befreit wird"],
    "examples_de": [["Krankenhausgeräte durchlaufen zwischen Patienten eine gründliche **Sterilisation**", "Die **Sterilisierung** chirurgischer Instrumente verhindert Infektionen"]]
  },
  {
    "lemma": "sterility",
    "meanings_de": ["Unfruchtbarkeit", "Keimfreiheit"],
    "definitions_de": ["Zustand der Unfähigkeit, Nachkommen oder Samen zu produzieren", "Zustand der Freiheit von Bakterien oder anderen lebenden Mikroorganismen"],
    "examples_de": [["Das Paar suchte nach der Entdeckung seiner **Unfruchtbarkeit** eine Behandlung", "Einige Medikamente können bei Patienten vorübergehende **Sterilität** verursachen"], ["Das Labor hält bei allen Verfahren strenge **Keimfreiheit** ein", "Die **Sterilität** des Operationssaals ist für die Patientensicherheit entscheidend"]]
  },
  {
    "lemma": "sterilization",
    "meanings_de": ["Dekontaminierungsprozess", "Fortpflanzungsverhinderung"],
    "definitions_de": ["Prozess, bei dem etwas vollständig sauber und frei von Bakterien gemacht wird", "Medizinisches Verfahren zur dauerhaften Verhinderung der Fortpflanzung"],
    "examples_de": [["Die Zahnarztpraxis befolgt strenge **Sterilisationsprotokolle** für alle Werkzeuge", "Die ordnungsgemäße **Sterilisation** von Babyflaschen verhindert schädliche Bakterien"], ["Sie wählte die **Sterilisation** als dauerhafte Verhütungsmethode", "Die **Kastration** von Haustieren hilft, die Tierpopulation zu kontrollieren"]]
  },
  {
    "lemma": "sterling",
    "meanings_de": ["britische Währung", "Silberlegierung"],
    "definitions_de": ["Britisches Geldsystem basierend auf dem Pfund", "Hochwertiges Silber mit 92,5 Prozent reinem Silber"],
    "examples_de": [["Der Preis war in Pfund **Sterling** angegeben", "Das **Pfund Sterling** schwankt weiterhin gegenüber dem Dollar"], ["Das **Sterlingsilber**-Teeservice ihrer Großmutter war ein Familienerbstück", "Der Juwelier überprüfte die **Sterling**-Markierung auf dem Armband"]]
  },
  {
    "lemma": "stern",
    "meanings_de": ["Schiffsheck"],
    "definitions_de": ["Hinterer Teil eines Schiffs oder Boots"],
    "examples_de": [["Der Kapitän stand am **Heck** und beobachtete den Sonnenuntergang", "Wellen schlugen während des Sturms über das **Heck**"]]
  }
]