[
  {
    "lemma": "crease",
    "meanings_de": ["Faltenmarke", "Oberflächenfalte"],
    "definitions_de": ["Linie oder Kante, die durch Falten, Pressen oder Zusammendrücken eines Materials entsteht", "kleine Falte oder Runzel, die sich auf einer Oberfläche bildet"],
    "examples_de": [["Sie bügelte das Hemd, um jede **Falte** zu entfernen", "Die **Bügelfalte** in der Mitte zeigt, wo gefaltet werden soll"], ["Zeit und Stress hinterließen tiefe **Falten** um seine Augen", "Das Leder entwickelte mit der Zeit natürliche **Knitterfalten**"]]
  },
  {
    "lemma": "creatine",
    "meanings_de": ["Muskelenergiestoff"],
    "definitions_de": ["organische Verbindung im Muskelgewebe, die Energie für Muskelkontraktionen bei hochintensiven Aktivitäten bereitstellt"],
    "examples_de": [["Sportler nehmen oft **Kreatin**-Präparate zur Leistungssteigerung", "Der Körper produziert **Kreatin** natürlich in Leber und Nieren"]]
  },
  {
    "lemma": "creationism",
    "meanings_de": ["Schöpfungslehre"],
    "definitions_de": ["religiöse Überzeugung, dass Leben und Universum von einem göttlichen Wesen erschaffen wurden und nicht durch natürliche Prozesse entstanden"],
    "examples_de": [["Die Schulbehörde diskutierte, ob der **Kreationismus** neben der Evolution gelehrt werden sollte", "Der **Kreationismus** lehnt wissenschaftliche Theorien zur Entstehung der Arten ab"]]
  },
  {
    "lemma": "credence",
    "meanings_de": ["Glaubwürdigkeit"],
    "definitions_de": ["Akzeptanz von etwas als wahr oder gültig basierend auf Vertrauen in die Quelle oder Beweise"],
    "examples_de": [["Die Zeugenaussage verlieh ihrem Alibi **Glaubwürdigkeit**", "Wissenschaftler schenken unbewiesenen Theorien keine **Glaubwürdigkeit**"]]
  },
  {
    "lemma": "credential",
    "meanings_de": ["Qualifikationsnachweis"],
    "definitions_de": ["Dokument oder Zertifikat, das die Qualifikationen, Leistungen oder Befugnisse einer Person in einem bestimmten Bereich nachweist"],
    "examples_de": [["Sie legte dem Einstellungskomitee ihre **Lehrbefähigung** vor", "Der Sicherheitsdienst überprüfte am Eingang die **Ausweise** aller Besucher"]]
  },
  {
    "lemma": "creditor",
    "meanings_de": ["Geldgeber"],
    "definitions_de": ["Person oder Institution, der von einer anderen Partei Geld geschuldet wird"],
    "examples_de": [["Das Unternehmen verhandelte mit den **Gläubigern** über eine Umschuldung", "Mehrere **Gläubiger** meldeten Forderungen gegen das insolvente Unternehmen an"]]
  },
  {
    "lemma": "credo",
    "meanings_de": ["persönliches Glaubensbekenntnis"],
    "definitions_de": ["Aussage über Überzeugungen oder Prinzipien, die jemandes Handlungen und Entscheidungen leiten"],
    "examples_de": [["Ihr persönliches **Credo** stellte Ehrlichkeit über alles andere", "Das **Leitbild** des Unternehmens konzentrierte sich auf Kundenzufriedenheit und Innovation"]]
  },
  {
    "lemma": "creed",
    "meanings_de": ["formelles Glaubenssystem"],
    "definitions_de": ["formelle Erklärung religiöser Überzeugungen oder Prinzipien, die von einer Kirche oder Gruppe akzeptiert werden"],
    "examples_de": [["Die Gemeinde sprach während des Sonntagsgottesdienstes das apostolische **Glaubensbekenntnis**", "Menschen jeden **Glaubens** versammelten sich zur Förderung religiöser Toleranz"]]
  },
  {
    "lemma": "creep",
    "meanings_de": ["unangenehme Person", "langsame Bewegung"],
    "definitions_de": ["Person, die sich auf unangenehme oder verstörende Weise verhält", "sehr langsame Bewegung oder allmähliche Positionsänderung"],
    "examples_de": [["Dieser **Widerling** folgte ihr die ganze Party über", "Sie mied den **Ekelpaketen**, der unangebrachte Kommentare machte"], ["Das langsame **Kriechen** der Ranke die Wand hinauf dauerte mehrere Monate", "Der Verkehr bewegte sich während der Hauptverkehrszeit im **Schneckentempo**"]]
  },
  {
    "lemma": "creeper",
    "meanings_de": ["Kletterpflanze", "kriechendes Wesen"],
    "definitions_de": ["Pflanze, die am Boden entlang wächst oder an Wänden und anderen Oberflächen klettert", "kleines Tier oder Insekt, das sich kriechend fortbewegt"],
    "examples_de": [["Die **Kletterpflanze** Efeu bedeckte die gesamte Backsteinmauer", "Der wilde Wein als **Rankpflanze** verfärbt sich im Herbst leuchtend rot"], ["Verschiedene **Kriechtiere** bewohnten den Waldboden unter umgefallenen Baumstämmen", "Das winzige **Krabbeltier** bewegte sich lautlos über die Zimmerdecke"]]
  },
  {
    "lemma": "creeping",
    "meanings_de": ["schleichender Fortschritt"],
    "definitions_de": ["langsame, allmähliche und oft unwillkommene Entwicklung oder Ausbreitung von etwas"],
    "examples_de": [["Die **schleichende** Inflation beunruhigte Ökonomen und Politiker", "Ein **schleichendes** Gefühl der Angst breitete sich aus, als die Deadline näher rückte"]]
  },
  {
    "lemma": "cremation",
    "meanings_de": ["Feuerbestattung"],
    "definitions_de": ["Beseitigung eines Leichnams durch Verbrennung zu Asche, typischerweise als Teil der Bestattungsriten"],
    "examples_de": [["Die Familie entschied sich für eine **Einäscherung** anstelle einer traditionellen Erdbestattung", "Die Kosten einer **Feuerbestattung** sind in der Regel niedriger als die einer Friedhofsbeerdigung"]]
  },
  {
    "lemma": "crematorium",
    "meanings_de": ["Einäscherungsanlage"],
    "definitions_de": ["Gebäude, in dem Leichname eingeäschert werden, typischerweise mit Öfen und zeremoniellen Räumen ausgestattet"],
    "examples_de": [["Der Trauerzug erreichte das **Krematorium** für die letzten Riten", "Das **Krematorium** führte mehrere Bestattungen am Tag durch"]]
  },
  {
    "lemma": "creole",
    "meanings_de": ["Mischsprache", "Kulturgruppe"],
    "definitions_de": ["Sprache, die sich aus der Vermischung von zwei oder mehr Sprachen entwickelt", "Person gemischter europäischer und afrikanischer Abstammung, besonders in karibischen Regionen"],
    "examples_de": [["Das haitianische **Kreol** verbindet französische mit afrikanischen Sprachelementen", "Das Louisiana-**Kreolisch** entwickelte sich aus Französisch, Spanisch und afrikanischen Sprachen"], ["Die **kreolische** Gemeinschaft bewahrte über Generationen ihre eigenen kulturellen Traditionen", "Viele **kreolische** Familien können ihre Abstammung bis in die Kolonialzeit zurückverfolgen"]]
  },
  {
    "lemma": "crepe",
    "meanings_de": ["Kreppstoff", "dünner Pfannkuchen"],
    "definitions_de": ["leichter, dünner Stoff mit gekräuselter Oberfläche für Kleidung und Dekorationen", "sehr dünner Pfannkuchen, der typischerweise mit süßen oder herzhaften Füllungen serviert wird"],
    "examples_de": [["Sie trug ein elegantes Kleid aus schwarzem **Krepp**", "Die **Krepppapier**-Dekorationen brachten Farbe in die Party"], ["Das Restaurant servierte mit Schokolade gefüllte **Crêpes** zum Nachtisch", "Er bestellte herzhafte **Crêpes** mit Pilzen und Käse"]]
  },
  {
    "lemma": "crescendo",
    "meanings_de": ["Lautstärkesteigerung", "Höhepunkt"],
    "definitions_de": ["allmähliche Zunahme der Lautstärke oder Intensität des Klangs in der Musik", "höchster oder intensivster Punkt einer allmählichen Steigerung"],
    "examples_de": [["Das Orchester steigerte sich zu einem dramatischen **Crescendo** im Finale", "Das **Crescendo** der Trommeln signalisierte den emotionalen Höhepunkt des Liedes"], ["Die Proteste erreichten kurz vor der Wahl ihr **Crescendo**", "Die Kontroverse steigerte sich über mehrere Wochen zum **Höhepunkt**"]]
  },
  {
    "lemma": "crescent",
    "meanings_de": ["Sichelform"],
    "definitions_de": ["gebogene Form, die einem Kreissegment ähnelt, wie der sichtbare Teil des Mondes im ersten oder letzten Viertel"],
    "examples_de": [["Die **Mondsichel** hing tief am Abendhimmel", "Sie trug eine zarte Halskette mit einem silbernen **Halbmond**-Anhänger"]]
  },
  {
    "lemma": "crest",
    "meanings_de": ["Gipfelpunkt", "Kopfschmuck", "Wappensymbol"],
    "definitions_de": ["höchster Punkt oder Spitze von etwas wie einem Hügel oder einer Welle", "Federbusch oder Haarbüschel auf dem Kopf eines Tieres", "Emblem oder Wappen, das eine Familie oder Organisation repräsentiert"],
    "examples_de": [["Sie erreichten nach Stunden endlich den **Gipfel** des Berges", "Surfer warteten darauf, dass die Wellen ihren **Kamm** erreichten"], ["Der rote **Kamm** des Hahns stellte sich auf, wenn er alarmiert war", "Der Kakadu hob aufgeregt seinen gelben **Federbusch**"], ["Das Familien**wappen** schmückte den Eingang zu ihrem Anwesen", "Jeder Ritter trug sein **Wappen** stolz auf Schild und Banner"]]
  },
  {
    "lemma": "crevasse",
    "meanings_de": ["Gletscherspalte"],
    "definitions_de": ["tiefer offener Riss in einem Gletscher oder Eisschild, der durch Bewegung und Spannung entsteht"],
    "examples_de": [["Der Bergsteiger umging vorsichtig die gefährliche **Gletscherspalte**", "Frischer Schnee verbirgt oft **Spalten** vor ahnungslosen Kletterern"]]
  },
  {
    "lemma": "crevice",
    "meanings_de": ["Felsspalte"],
    "definitions_de": ["schmale Öffnung oder Riss in Fels, Mauer oder anderer harter Oberfläche"],
    "examples_de": [["Kleine Pflanzen wuchsen aus **Ritzen** in der alten Steinmauer", "Die Eidechse verschwand in einer **Felsspalte** zwischen den Steinen"]]
  },
  {
    "lemma": "crewman",
    "meanings_de": ["Besatzungsmitglied"],
    "definitions_de": ["Mitglied einer Schiffsbesatzung, das verschiedene Aufgaben an Bord des Schiffes ausführt"],
    "examples_de": [["Jedes **Besatzungsmitglied** hatte während der Reise spezifische Verantwortlichkeiten", "Der Kapitän lobte jeden **Matrosen** für seine harte Arbeit"]]
  },
  {
    "lemma": "crib",
    "meanings_de": ["Babybett", "Spickzettel"],
    "definitions_de": ["kleines Bett mit hohen Seiten für Babys und Kleinkinder", "schriftliche Notizen, die unehrlich während einer Prüfung oder als schnelle Referenz verwendet werden"],
    "examples_de": [["Das Baby schlief friedlich in seinem hölzernen **Gitterbett**", "Sie bauten das neue **Kinderbett** auf, bevor das Baby ankam"], ["Studenten, die beim Benutzen eines **Spickzettels** erwischt werden, müssen mit ernsten akademischen Konsequenzen rechnen", "Er fertigte einen kleinen **Schummelzettel** mit den wichtigsten Formeln für den Test an"]]
  },
  {
    "lemma": "crick",
    "meanings_de": ["Nackenverspannung"],
    "definitions_de": ["schmerzhafte Steifheit in Nacken- oder Rückenmuskeln durch Überanstrengung oder ungünstige Position"],
    "examples_de": [["Sie wachte mit einer schrecklichen **Nackenverspannung** auf", "Der lange Flug verursachte einen **steifen Hals** zwischen seinen Schultern"]]
  },
  {
    "lemma": "cricket",
    "meanings_de": ["zirpendes Insekt", "Schlagballspiel"],
    "definitions_de": ["kleines springendes Insekt, das zirpende Geräusche macht, indem es seine Flügel aneinander reibt", "Mannschaftssport mit Schläger, Ball und Wickets, der in vielen Ländern beliebt ist"],
    "examples_de": [["Das Zirpen der **Grille** erfüllte den warmen Sommerabend", "Eine **Grille** hüpfte über den Gartenweg"], ["England gewann das **Cricket**-Spiel im letzten Durchgang", "Er spielte **Cricket** für seine Universitätsmannschaft"]]
  },
  {
    "lemma": "cricketer",
    "meanings_de": ["Cricketspieler"],
    "definitions_de": ["Person, die Cricket professionell oder als ernsthaftes Hobby spielt"],
    "examples_de": [["Der berühmte **Cricketspieler** gab jungen Fans Autogramme", "Mehrere internationale **Cricketspieler** nahmen am Wohltätigkeitsspiel teil"]]
  },
  {
    "lemma": "crier",
    "meanings_de": ["Ausrufer"],
    "definitions_de": ["Person, die öffentliche Bekanntmachungen auf Straßen oder vor Gericht macht, besonders in früheren Zeiten"],
    "examples_de": [["Der Stadt**ausrufer** läutete seine Glocke, bevor er Proklamationen verlas", "Mittelalterliche **Ausrufer** verbreiteten Neuigkeiten in Dörfern und Städten"]]
  },
  {
    "lemma": "criminality",
    "meanings_de": ["Kriminalität"],
    "definitions_de": ["Zustand oder Eigenschaft, kriminell zu sein oder die Neigung, Verbrechen zu begehen"],
    "examples_de": [["Steigende Armut korreliert oft mit erhöhter **Kriminalität** in städtischen Gebieten", "Die Studie untersuchte Faktoren, die zur Jugend**kriminalität** beitragen"]]
  },
  {
    "lemma": "criminalization",
    "meanings_de": ["Kriminalisierung"],
    "definitions_de": ["Prozess, etwas illegal zu machen, indem Gesetze verabschiedet werden, die es als Straftat definieren"],
    "examples_de": [["Die **Kriminalisierung** bestimmter Drogen bleibt ein umstrittenes politisches Thema", "Aktivisten lehnten die **Kriminalisierung** friedlicher Protestaktivitäten ab"]]
  },
  {
    "lemma": "criminologist",
    "meanings_de": ["Kriminologe"],
    "definitions_de": ["Experte, der Verbrechen, kriminelles Verhalten und das Strafjustizsystem wissenschaftlich untersucht"],
    "examples_de": [["Der **Kriminologe** sagte über Verhaltensmuster bei Serientätern aus", "Führende **Kriminologen** berieten die Regierung bei der Gefängnisreform"]]
  },
  {
    "lemma": "criminology",
    "meanings_de": ["Kriminologie"],
    "definitions_de": ["wissenschaftliche Untersuchung von Verbrechen, Verbrechern, kriminellem Verhalten und dem Strafjustizsystem"],
    "examples_de": [["Sie promovierte in **Kriminologie** an einer renommierten Universität", "Die moderne **Kriminologie** nutzt Datenanalyse zur Vorhersage von Verbrechensmustern"]]
  },
  {
    "lemma": "crimp",
    "meanings_de": ["Pressfalte", "Hemmfaktor"],
    "definitions_de": ["Falte, Knick oder Welle, die durch Pressen oder Kneifen entsteht", "etwas, das Fortschritt oder Entwicklung einschränkt oder behindert"],
    "examples_de": [["Die Friseurin fügte **Kräuselungen** hinzu, um dem Haar mehr Volumen zu verleihen", "Eine **Knickstelle** im Metallrohr schränkte den Wasserfluss ein"], ["Steigende Kosten setzten ihren Expansionsplänen einen **Dämpfer** auf", "Schlechtes Wetter wirkte sich **hemmend** auf die Besucherzahlen des Freiluftfestivals aus"]]
  },
  {
    "lemma": "crimson",
    "meanings_de": ["Karmesinrot"],
    "definitions_de": ["sattes, tiefes Rot ähnlich der Farbe von frischem Blut"],
    "examples_de": [["Der Sonnenuntergang malte den Himmel in leuchtenden **karmesinroten** Tönen", "Sie trug ein atemberaubendes **purpurrotes** Kleid zur Gala"]]
  },
  {
    "lemma": "cringe",
    "meanings_de": ["Fremdscham"],
    "definitions_de": ["körperliche Bewegung des Zurückweichens oder Zusammenzuckens aus Verlegenheit, Angst oder Ekel"],
    "examples_de": [["Seine peinliche Rede löste beim gesamten Publikum **Fremdscham** aus", "Sie spürte ein **Zusammenzucken** vor Verlegenheit, als sie sich an ihren Fehler erinnerte"]]
  },
  {
    "lemma": "cripple",
    "meanings_de": ["Behinderter"],
    "definitions_de": ["veralteter und beleidigender Begriff für eine Person mit körperlicher Behinderung, die die Bewegung beeinträchtigt"],
    "examples_de": [["Die moderne Sprache vermeidet die Verwendung von **Krüppel** als Substantiv für Menschen", "Historische Texte enthalten oft das Wort **Krüppel** in unangemessener Weise"]]
  },
  {
    "lemma": "crisp",
    "meanings_de": ["Knabberei"],
    "definitions_de": ["dünne Scheibe Kartoffel oder anderes Gemüse, die knusprig frittiert und als Snack gegessen wird"],
    "examples_de": [["Sie öffnete eine Tüte **Chips**, um sie während des Films zu teilen", "Die Kneipe servierte zu jedem Getränk frische **Kartoffelchips**"]]
  },
  {
    "lemma": "criterion",
    "meanings_de": ["Beurteilungsmaßstab"],
    "definitions_de": ["Prinzip oder Standard, nach dem etwas beurteilt, entschieden oder bewertet wird"],
    "examples_de": [["Die akademische Leistung war das Haupt**kriterium** für die Stipendienvergabe", "Das Einstellungskomitee legte klare **Kriterien** für die Bewertung der Kandidaten fest"]]
  },
  {
    "lemma": "criticality",
    "meanings_de": ["Kritikalität"],
    "definitions_de": ["Zustand von kritischer Wichtigkeit oder das Erreichen eines entscheidenden Punktes, der sofortige Aufmerksamkeit erfordert"],
    "examples_de": [["Ingenieure bewerteten die **Kritikalität** jedes Systemkomponentenausfalls", "Die Situation erreichte **Kritikalität**, als die Vorräte gefährlich knapp wurden"]]
  },
  {
    "lemma": "crochet",
    "meanings_de": ["Häkelhandwerk"],
    "definitions_de": ["Handarbeitstechnik, bei der mit einer Häkelnadel Stoff aus Garn- oder Fadenschlaufen hergestellt wird"],
    "examples_de": [["Ihre Großmutter brachte ihr das **Häkeln** bei, als sie jung war", "Das komplizierte **Häkelmuster** erforderte stundenlange geduldige Arbeit"]]
  },
  {
    "lemma": "crockery",
    "meanings_de": ["Geschirr"],
    "definitions_de": ["Teller, Schüsseln, Tassen und andere Essutensilien aus Steingut oder Porzellan"],
    "examples_de": [["Die Hochzeitsliste enthielt ein teures **Geschirrset**", "Sie wusch das antike **Geschirr** vorsichtig von Hand"]]
  },
  {
    "lemma": "crocodile",
    "meanings_de": ["Krokodil"],
    "definitions_de": ["großes Raubtierreptil mit langen Kiefern, kräftigem Schwanz und gepanzerter Haut, das in tropischen Gewässern lebt"],
    "examples_de": [["Das **Krokodil** lauerte knapp unter der trüben Oberfläche des Flusses", "Australische Salzwasser**krokodile** können über sechs Meter lang werden"]]
  },
  {
    "lemma": "crone",
    "meanings_de": ["alte Frau"],
    "definitions_de": ["alte Frau, die in Folklore und Geschichten oft als hässlich oder bösartig dargestellt wird"],
    "examples_de": [["Das Märchen handelte von einer geheimnisvollen **Alten**, die im Wald lebte", "Die weise **Greisin** gab dem jungen Helden kryptische Ratschläge"]]
  },
  {
    "lemma": "cronyism",
    "meanings_de": ["Vetternwirtschaft"],
    "definitions_de": ["Praxis, Freunde unabhängig von ihren Qualifikationen in Autoritätspositionen zu berufen"],
    "examples_de": [["Der Skandal deckte weit verbreitete **Vetternwirtschaft** bei der Vergabe von Regierungsaufträgen auf", "Die **Günstlingswirtschaft** untergrub das öffentliche Vertrauen in die Einstellungspraktiken der Verwaltung"]]
  },
  {
    "lemma": "crook",
    "meanings_de": ["Gauner", "Hirtenstab"],
    "definitions_de": ["Person, die sich an unehrlichen oder kriminellen Aktivitäten beteiligt", "gebogener Stock, der von Hirten oder als Gehhilfe verwendet wird"],
    "examples_de": [["Die Polizei verhaftete den **Gauner** nach monatelangen Ermittlungen", "Der **Betrüger** hatte Dutzende älterer Opfer betrogen"], ["Der Hirte benutzte seinen **Krummstab**, um die Schafe durch das Tor zu führen", "Der Bischof trug während der Zeremonie einen kunstvollen **Hirtenstab**"]]
  },
  {
    "lemma": "crooner",
    "meanings_de": ["Schmusesänger"],
    "definitions_de": ["Sänger, der sentimentale Lieder in einem weichen, geschmeidigen Stil vorträgt"],
    "examples_de": [["Der berühmte **Schnulzensänger** unterhielt das Publikum mit romantischen Balladen", "Frank Sinatra bleibt einer der beliebtesten **Crooner** der Geschichte"]]
  },
  {
    "lemma": "crooning",
    "meanings_de": ["Schmusesingen"],
    "definitions_de": ["Art des Singens in einer weichen, sentimentalen Weise, die typischerweise mit romantischen Liedern verbunden ist"],
    "examples_de": [["Sein sanftes **Säuseln** machte das Liebeslied besonders berührend", "Das leise **Summen** der Mutter half dem Baby beim Einschlafen"]]
  }
]